trunklucator/__init__.py
trunklucator/trunklucator.py
trunklucator/base/__init__.py
trunklucator/base/dto.py
trunklucator/const/__init__.py
trunklucator/const/msg.py
trunklucator/const/payload.py
trunklucator/const/task_types.py
trunklucator/frontend/html_field/app.js
trunklucator/frontend/html_field/content.css
trunklucator/frontend/html_field/grid.css
trunklucator/frontend/html_field/index.html
trunklucator/frontend/html_field/lib/onmessage.js
trunklucator/frontend/html_field/lib/reconnecting-websocket.js
trunklucator/frontend/simple/index.html
trunklucator/protocol/__init__.py
trunklucator/protocol/create.py
trunklucator/protocol/dto.py
trunklucator/protocol/test/__init__.py
trunklucator/protocol/test/test_dto.py
trunklucator/webserver/__init__.py
trunklucator/webserver/aiothread.py
trunklucator/webserver/server.py
trunklucator-1.0.7.dist-info/LICENSE
trunklucator-1.0.7.dist-info/METADATA
trunklucator-1.0.7.dist-info/WHEEL
trunklucator-1.0.7.dist-info/top_level.txt
trunklucator-1.0.7.dist-info/RECORD
