Metadata-Version: 2.1
Name: trunklucator
Version: 1.0.7
Summary: Easy plugable UI for your experiments with data and machine learning
Home-page: https://github.com/Dumbris/trunklucator
License: Apache License 2.0
Platform: any
Classifier: Development Status :: 4 - Beta
Classifier: Environment :: Web Environment
Classifier: Intended Audience :: Developers
Classifier: Intended Audience :: System Administrators
Classifier: License :: OSI Approved :: Apache Software License
Classifier: Operating System :: OS Independent
Classifier: Programming Language :: Python
Classifier: Programming Language :: Python :: 3
Classifier: Programming Language :: Python :: 3.2
Classifier: Programming Language :: Python :: 3.3
Classifier: Programming Language :: Python :: 3.4
Classifier: Topic :: Scientific/Engineering :: Information Analysis
Requires-Python: >3.6.0
Requires-Dist: aiohttp
